{"nodes": [{"id": "home_teness_it_fracas_backend_evacuation_admin_py", "label": "admin.py", "file_type": "code", "source_file": "backend/evacuation/admin.py", "source_location": "L1"}, {"id": "home_teness_it_fracas_backend_evacuation_admin_evacuationcenteradmin", "label": "EvacuationCenterAdmin", "file_type": "code", "source_file": "backend/evacuation/admin.py", "source_location": "L8", "_callable": true}, {"id": "gismodeladmin", "label": "GISModelAdmin", "file_type": "code", "source_file": "", "source_location": ""}], "edges": [{"source": "home_teness_it_fracas_backend_evacuation_admin_py", "target": "django_contrib_gis_admin", "relation": "imports_from", "context": "import", "confidence": "EXTRACTED", "source_file": "backend/evacuation/admin.py", "source_location": "L1", "weight": 1.0}, {"source": "home_teness_it_fracas_backend_evacuation_admin_py", "target": "django_contrib", "relation": "imports_from", "context": "import", "confidence": "EXTRACTED", "source_file": "backend/evacuation/admin.py", "source_location": "L2", "weight": 1.0}, {"source": "home_teness_it_fracas_backend_evacuation_admin_py", "target": "home_teness_it_fracas_backend_evacuation_models_py", "relation": "imports_from", "context": "import", "confidence": "EXTRACTED", "source_file": "backend/evacuation/admin.py", "source_location": "L4", "weight": 1.0}, {"source": "home_teness_it_fracas_backend_evacuation_admin_py", "target": "home_teness_it_fracas_backend_evacuation_admin_evacuationcenteradmin", "relation": "contains", "confidence": "EXTRACTED", "source_file": "backend/evacuation/admin.py", "source_location": "L8", "weight": 1.0}, {"source": "home_teness_it_fracas_backend_evacuation_admin_evacuationcenteradmin", "target": "gismodeladmin", "relation": "inherits", "confidence": "EXTRACTED", "source_file": "backend/evacuation/admin.py", "source_location": "L8", "weight": 1.0}], "raw_calls": []}